<?xml version="1.0" standalone="no" ?>
<!DOCTYPE interviews SYSTEM "interview.dtd">

<!--
	EXPECTED RETURN RESULTS
	Q2: STAFF 01, 03, 05
-->

<interviews>
	<interview rID="RES01" pID="JOB01" sID="STAFF01">
		<date>Nov 28, 2014</date>
		<time>15:33</time>
		<location>Hell</location>
		<assessment>
			<answers>
				<answer qID="Q01">0</answer>
				<answer qID="Q02">10</answer>
				<answer qID="Q03">96</answer>
				<answer qID="Q04">33</answer>
				<answer qID="Q05">46</answer>
			</answers>
			<techProficiency>12</techProficiency>
			<communication>96</communication>
			<enthusiasm>74</enthusiasm>
			<collegiality>3</collegiality>
		</assessment>
	</interview>	

	<interview rID="RES02" pID="JOB02" sID="STAFF01">
		<date>June 28, 2014</date>
		<time>11:46</time>
		<location>Igloolik</location>
		<assessment>
			<answers>
				<answer qID="Q01">54</answer>
				<answer qID="Q02">16</answer>
				<answer qID="Q03">100</answer>
				<answer qID="Q05">0</answer>
			</answers>
			<techProficiency>100</techProficiency>
			<communication>16</communication>
			<enthusiasm>0</enthusiasm>
		</assessment>
	</interview>

	<interview rID="RES03" pID="JOB01" sID="STAFF02">
		<date>September 11, 2001</date>
		<time>11:11</time>
		<location>Pluto</location>
		<assessment>
			<techProficiency>100</techProficiency>
			<communication>16</communication>
			<enthusiasm>0</enthusiasm>
			<collegiality>38</collegiality>
		</assessment>
	</interview>

	<interview rID="RES04" pID="JOB01" sID="STAFF03">
		<date>February 14, 1969</date>
		<time>19:54</time>
		<location>Montreal</location>
		<assessment>
			<techProficiency>10</techProficiency>
			<communication>93</communication>
			<enthusiasm>93</enthusiasm>
		</assessment>
	</interview>

	<!-- FOR THE EXAMPLE IN THE HANDOUT FOR Q8 -->
	<interview rID="RES06" pID="JOB03" sID="STAFF05">
		<date>February 14, 1969</date>
		<time>19:54</time>
		<location>Montreal</location>
		<assessment>
			<techProficiency>10</techProficiency>
			<communication>93</communication>
			<enthusiasm>93</enthusiasm>
		</assessment>
	</interview>

	<interviewer sID="STAFF01"> 
		<forename>Jeffrey</forename>
		<surname>Steele</surname>
		<honorific>Mixter</honorific>
		<honorific>Admiral</honorific>
		<honorific>Doctor</honorific>
		<honorific>Queen</honorific>
		<honorific>Lord</honorific>
		<title>Dungeon Master</title>
	</interviewer>

	<interviewer sID="STAFF02"> 
		<forename>Maury</forename>
		<surname>Povich</surname>
		<honorific>Master</honorific>
	</interviewer>

	<interviewer sID="STAFF03"> 
		<forename>Atanaarjuat</forename>
		<surname>Alorut</surname>
		<honorific>Captain</honorific>
		<title>The fastest runner</title>
	</interviewer>

	<interviewer sID="STAFF04"> 
		<forename>Puja</forename>
		<surname>Atsuli</surname>
		<honorific>Miss</honorific>
		<title>Bus driver</title>
	</interviewer>

	<!-- FOR THE EXAMPLE IN THE HANDOUT FOR Q8 -->
	<interviewer sID="STAFF05"> 
		<forename>Taisha</forename>
		<surname>Robinson</surname>
		<honorific>Mistress</honorific>
		<title>Dungeon master</title>
	</interviewer>
</interviews>	
